jinja_tornado/__init__.py
jinja_tornado/jinja_tornado.py
jinja_tornado-0.1.3.dist-info/LICENSE
jinja_tornado-0.1.3.dist-info/METADATA
jinja_tornado-0.1.3.dist-info/WHEEL
jinja_tornado-0.1.3.dist-info/top_level.txt
jinja_tornado-0.1.3.dist-info/RECORD
