Metadata-Version: 2.1
Name: jinja-tornado
Version: 0.1.3
Summary: jinja2 template support for tornado web framework
Home-page: https://github.com/westurner/jinja_tornado
Author: thkang2, westurner
Author-email: wes@wrd.nu
License: MIT License
Platform: UNKNOWN
Requires-Dist: tornado
Requires-Dist: Jinja2
